{
  "bookingReference": "APPLE20241026153212",
  "voyageDetails": {
    "vesselName": "CMA CGM BOUGAINVILLE",
    "voyageNumber": "2428E",
    "bound": "W"
  },
  "routeDetails": {
    "placeOfReceipt": "SINGAPORE",
    "portOfLoading": "SINGAPORE",
    "portOfDischarge": "ROTTERDAM",
    "placeOfDelivery": "ROTTERDAM",
    "finalDestination": ""
  },
  "paymentDetails": {
    "freightPaymentTerms": "COLLECT",
    "freightPayableAt": "SINGAPORE"
  },
  "documentationDetails": {
    "blType": "SEA WAYBILL",
    "numberOfOriginalBLs": 3,
    "numberOfCopies": 0
  },
  "partyDetails": {
    "shipper": {
      "name": "SCHULTE GMBH & CO. KG",
      "address": "WALTER-RATZ-STRASSE 3, 21079 HAMBURG, GERMANY",
      "telephone": "+49 40 369060",
      "email": "INFO@SCHULTE-GMBH.DE"
    },
    "consignee": {
      "name": "ASIA PACIFIC TRADING PTE LTD",
      "address": "16 RAFFLES QUAY #32-01, SINGAPORE 048581",
      "taxId": "200212345H",
      "president": "MR. LIM CHONG WEN",
      "telephone": "+65 6536 8888",
      "fax": "+65 6536 9999"
    },
    "notifyParty": {
      "name": "SCHULTE GMBH & CO. KG",
      "address": "WALTER-RATZ-STRASSE 3, 21079 HAMBURG, GERMANY",
      "telephone": "+49 40 369060",
      "email": "INFO@SCHULTE-GMBH.DE"
    }
  },
  "shippingTerm": "CFR",
  "hsCode": "84139100",
  "commodityDescription": "PUMPS FOR LIQUIDS, OTHER THAN HYDRAULIC",
  "containers": [
    {
      "containerNumber": "CRLU9672315",
      "sealNumber": "123456",
      "marksAndNumbers": "AS PER ATTACHED RIDER",
      "numberOfPackages": 5,
      "packageType": "CRATES",
      "cargoDescription": "SHIPPER'S LOAD, COUNT & WEIGHT, SOTW & SEAL SAID TO CONTAIN: CFR SINGAPORE PUMPS FOR LIQUIDS, OTHER THAN HYDRAULIC",
      "grossWeight": 4500.0,
      "measurement": 10.0
    }
  ],
  "totalShipment": {
    "totalContainers": "ONE (20' DRY) CONTAINER ONLY",
    "totalPackages": 5,
    "packageType": "CRATES",
    "containerType": "20 DRY",
    "totalGrossWeight": 4500.0,
    "totalMeasurement": 10.0
  },
  "outOfGaugeDimensions": {
    "length": "In-Gauge",
    "width": "In-Gauge",
    "height": "In-Gauge",
    "additionalInfo": "In-gauge in 20' DRY Container"
  },
  "additionalInformation": {
    "lcDetails": {
      "lcNumber": "01234567890"
    },
    "certificateDetails": "123456789012345",
    "originalBLDistribution": {
      "name": "DHL EXPRESS SINGAPORE",
      "address": "25 CHANDLER ROAD #01-01, SINGAPORE 199679",
      "telephone": "+65 6371 3100",
      "fax": "+65 6371 3111"
    },
    "originalInvoiceDistribution": {
      "name": "DHL EXPRESS SINGAPORE",
      "address": "25 CHANDLER ROAD #01-01, SINGAPORE 199679",
      "telephone": "+65 6371 3100",
      "fax": "+65 6371 3111"
    },
    "onboardDate": "OCT. 31. 2024",
    "additionalRemarks": "NONE"
  }
}