{
  "bookingReference": "APPLE20241015103022",
  "voyageDetails": {
    "vesselName": "APL CHANGI",
    "voyageNumber": "2442E",
    "bound": "E"
  },
  "routeDetails": {
    "placeOfReceipt": "HAMBURG",
    "portOfLoading": "HAMBURG",
    "portOfDischarge": "SHANGHAI",
    "placeOfDelivery": "SHANGHAI",
    "finalDestination": "FRANKFURT, GERMANY"
  },
  "paymentDetails": {
    "freightPaymentTerms": "PREPAID",
    "freightPayableAt": "SINGAPORE"
  },
  "documentationDetails": {
    "blType": "Sea Waybill",
    "numberOfOriginalBLs": 3,
    "numberOfCopies": 0
  },
  "partyDetails": {
    "shipper": {
      "name": "ASIA PACIFIC TRADING CO.",
      "address": "101 Anson Road #20-01, Singapore 079900",
      "telephone": "+65 6221 8900",
      "fax": "+65 6221 8999"
    },
    "consignee": {
      "name": "EUROTECH IMPORT GMBH",
      "address": "Mainzer Landstr. 123, 60329 Frankfurt am Main, Germany",
      "telephone": "+49 69 7560 8000",
      "fax": "+49 69 7560 8001"
    },
    "notifyParty": {
      "name": "EUROTECH LOGISTICS GMBH",
      "address": "Am Flughafen 12, 60549 Frankfurt am Main, Germany",
      "telephone": "+49 69 6950 5000",
      "fax": "+49 69 6950 5001"
    }
  },
  "shippingTerm": "CFR ROTTERDAM",
  "hsCode": "8479.89",
  "commodityDescription": "INDUSTRIAL MACHINERY PARTS",
  "containers": [
    {
      "containerNumber": "TCLU6572345",
      "sealNumber": "123456",
      "marksAndNumbers": "ET123",
      "numberOfPackages": 10,
      "packageType": "BOXES",
      "cargoDescription": "SHIPPER'S LOAD AND COUNT, SEAL SAID TO CONTAIN: INDUSTRIAL MACHINERY PARTS",
      "grossWeight": 12500.0,
      "measurement": 25.0
    }
  ],
  "totalShipment": {
    "totalContainers": "ONE (20' DRY) CONTAINER ONLY",
    "totalPackages": 10,
    "packageType": "BOXES",
    "totalGrossWeight": 12500.0,
    "totalMeasurement": 25.0
  },
  "dangerousGoods": {
    "containerNumber": "",
    "unClass": "",
    "unCode": "",
    "hsCode": "",
    "flashPoint": "",
    "additionalInfo": ""
  },
  "additionalInformation": {
    "purchaseOrderNumber": "PO1234567",
    "salesOrderNumber": "SO87654321",
    "lcDetails": {
      "lcNumber": "LC20241015"
    },
    "certificateDetails": "CERT-20241015-001",
    "originalBLDistribution": {
      "name": "ASIA PACIFIC TRADING CO.",
      "address": "101 Anson Road #20-01, Singapore 079900",
      "telephone": "+65 6221 8900",
      "fax": "+65 6221 8999"
    },
    "originalInvoiceDistribution": {
      "name": "EUROTECH IMPORT GMBH",
      "address": "Mainzer Landstr. 123, 60329 Frankfurt am Main, Germany",
      "telephone": "+49 69 7560 8000",
      "fax": "+49 69 7560 8001"
    },
    "onboardDate": "OCT. 20. 2024",
    "additionalRemarks": ""
  }
}