{
    "bookingReference": "CHERRY20240925091202",
    "shipperReference": "HY20240925-004",
    "voyageDetails": {
      "vesselName": "GREEN DOLPHIN",
      "voyageNumber": "2024060N",
      "bound": "N"
    },
    "routeDetails": {
      "placeOfReceipt": "ULSAN, KOREA",
      "portOfLoading": "ULSAN, KOREA",
      "portOfDischarge": "LONG BEACH, USA",
      "placeOfDelivery": "LOS ANGELES, USA",
      "finalDestination": "LOS ANGELES, USA"
    },
    "paymentDetails": {
      "freightPaymentTerms": "Prepaid",
      "freightPayableAt": "ULSAN, KOREA"
    },
    "documentationDetails": {
      "blType": "ORIGINAL",
      "numberOfOriginalBLs": 3,
      "numberOfCopies": 2
    },
    "partyDetails": {
      "shipper": {
        "name": "HYUNDAI MOTOR COMPANY",
        "address": "12, HEOLLEUNG-RO, SEOCHO-GU, SEOUL",
        "country": "KOREA",
        "additionalInfo": ""
      },
      "consignee": {
        "name": "HYUNDAI MOTOR AMERICA",
        "address": "10550 TALBERT AVENUE, FOUNTAIN VALLEY, CA 92708",
        "country": "USA",
        "email": "logistics@hmusa.com",
        "telephone": "+1 714 965 3000"
      },
      "notifyParty": {
        "name": "HYUNDAI MOTOR AMERICA",
        "address": "10550 TALBERT AVENUE, FOUNTAIN VALLEY, CA 92708",
        "country": "USA",
        "email": "logistics@hmusa.com",
        "telephone": "+1 714 965 3000"
      }
    },
    "shippingTerm": "CY / Door",
    "hsCode": "870323",
    "commodityDescription": "AUTOMOBILE PARTS",
    "containers": [
      {
        "containerNumber": "HYMU1122334",
        "sealNumber": "HY56789",
        "marksAndNumbers": "HYUNDAI PARTS",
        "numberOfPackages": 500,
        "packageType": "BOXES",
        "cargoDescription": "AUTOMOBILE ENGINE PARTS FOR HYUNDAI SONATA",
        "grossWeight": 22000.000,
        "unitOfgrossWeight": "KGS",
        "measurement": 55.000,
        "unitofMeasurement": "CBM"
      },
      {
        "containerNumber": "HYMU5566778",
        "sealNumber": "HY56790",
        "marksAndNumbers": "HYUNDAI PARTS",
        "numberOfPackages": 600,
        "packageType": "BOXES",
        "cargoDescription": "AUTOMOBILE BODY PARTS FOR HYUNDAI TUCSON",
        "grossWeight": 20000.000,
        "unitOfgrossWeight": "KGS",
        "measurement": 60.000,
        "unitofMeasurement": "CBM"
      }
    ],
    "totalShipment": {
      "totalContainers": "TWO (40'DV X2) CONTAINERS ONLY",
      "totalPackages": 1100,
      "unitOfMeasurement": "BOXES",
      "totalGrossWeight": 42000.000,
      "unitOfgrossWeight": "KGS",
      "totalMeasurement": 115.000,
      "unitofMeasurement": "CBM"
    },
    "additionalInformation": {
      "purchaseOrderNumber": "PO-HMA-2024-003",
      "hsCode": "870323",
      "freeTimeAtDestination": "10 DAYS",
      "lcDetails": {
        "lcNumber": "LC23456789012"
      },
      "certificateDetails": "USDOT-2024-789012",
      "originalBLDistribution": {
        "name": "HYUNDAI MOTOR AMERICA",
        "address": "10550 TALBERT AVENUE, FOUNTAIN VALLEY, CA 92708, USA",
        "telephone": "+1 714 965 3000"
      },
      "originalInvoiceDistribution": {
        "name": "HYUNDAI MOTOR COMPANY",
        "address": "12, HEOLLEUNG-RO, SEOCHO-GU, SEOUL, KOREA",
        "telephone": "+82 2 3464 1114",
        "fax": "+82 2 3464 3477"
      },
      "onboardDate": "OCT. 01. 2024",
      "additionalRemarks": "CONTAINS AUTOMOBILE PARTS - HANDLE WITH CARE"
    }
  }