{
  "bookingReference": "CHERRY202409156689",
  "customerName": "GLOBAL SHIPPING SOLUTIONS INC.",
  "shipperName": "ASIA PACIFIC TRADING CO.",
  "invoiceReceiver": "GLOBAL SHIPPING SOLUTIONS INC.",
  "voyageDetails": {
    "vesselName": "CMA CGM ZHENG HE",
    "voyageNumber": "244EWT"
  },
  "cargoDetails": {
    "hsCode": "84798990",
    "chapterDescription": "MACHINERY FOR WORKING TEXTILE FABRICS",
    "commodity": "TEXTILE LOOM SPARE PARTS"
  },
  "containerDetails": {
    "size": "40 HIGH CUBE CONTAINER",
    "type": "DRY",
    "quantity": 3
  },
  "routeDetails": {
    "placeOfReceipt": "NINGBO, CHINA",
    "portOfLoading": "NINGBO, CHINA",
    "portOfDischarge": "ROTTERDAM, NETHERLANDS",
    "placeOfDelivery": "ROTTERDAM, NETHERLANDS"
  },
  "scheduleDetails": {
    "estimatedArrivalAtLoadingPort": "2024-09-22 12:00",
    "estimatedDepartureFromLoadingPort": "2024-09-23 18:00",
    "estimatedArrivalAtDischargePort": "2024-10-17 08:00"
  },
  "emptyContainerPickupLocation": "NINGBO, CHINA",
  "shippingTerm": "CFR",
  "remarks": "SPECIAL HANDLING REQUIRED - FRAGILE CARGO"
}