{
  "bookingReference": "CHERRY202409083977",
  "customerName": "CUSTOMER 3570",
  "shipperName": "SHIPPER 7029",
  "invoiceReceiver": "INVOICE RECEIVER 3561",
  "voyageDetails": {
    "vesselName": "CMA CGM BENJAMIN FRANKLIN",
    "voyageNumber": "2024526E"
  },
  "cargoDetails": {
    "hsCode": "823280",
    "chapterDescription": "SAMPLE CHAPTER DESCRIPTION 25",
    "commodity": "SAMPLE COMMODITY 100"
  },
  "containerDetails": {
    "size": "40 DRY",
    "type": "REEFER CONTAINER",
    "quantity": 1
  },
  "routeDetails": {
    "placeOfReceipt": "GDANSK",
    "portOfLoading": "GDANSK",
    "portOfDischarge": "TANGER",
    "placeOfDelivery": "TANGER"
  },
  "scheduleDetails": {
    "estimatedArrivalAtLoadingPort": "2024-09-23 23:11",
    "estimatedDepartureFromLoadingPort": "2024-10-27 23:11",
    "estimatedArrivalAtDischargePort": "2024-11-15 23:11"
  },
  "emptyContainerPickupLocation": "TANGER, KOREA",
  "shippingTerm": "CPT",
  "remarks": "No special instructions"
}