{
  "bookingReference": "CHERRY202409135445",
  "customerName": "CUSTOMER 3070",
  "shipperName": "SHIPPER 8715",
  "invoiceReceiver": "INVOICE RECEIVER 7392",
  "voyageDetails": {
    "vesselName": "CMA CGM VASCO DE GAMA",
    "voyageNumber": "2024626E"
  },
  "cargoDetails": {
    "hsCode": "449305",
    "chapterDescription": "SAMPLE CHAPTER DESCRIPTION 5",
    "commodity": "SAMPLE COMMODITY 84"
  },
  "containerDetails": {
    "size": "45 HIGH CUBE",
    "type": "GENERAL PURPOSE",
    "quantity": 2
  },
  "routeDetails": {
    "placeOfReceipt": "LE HAVRE",
    "portOfLoading": "LE HAVRE",
    "portOfDischarge": "TANGER",
    "placeOfDelivery": "TANGER"
  },
  "scheduleDetails": {
    "estimatedArrivalAtLoadingPort": "2024-10-02 23:49",
    "estimatedDepartureFromLoadingPort": "2024-10-24 23:49",
    "estimatedArrivalAtDischargePort": "2024-11-10 23:49"
  },
  "emptyContainerPickupLocation": "YANTIAN, CHINA",
  "shippingTerm": "FCA",
  "remarks": "No special instructions"
}