{
  "bookingReference": "CHERRY202411031478",
  "customerName": "CUSTOMER 2364",
  "shipperName": "SHIPPER 5949",
  "invoiceReceiver": "INVOICE RECEIVER 9436",
  "voyageDetails": {
    "vesselName": "CMA CGM EOURES",
    "voyageNumber": "2024146W"
  },
  "cargoDetails": {
    "hsCode": "846099",
    "chapterDescription": "SAMPLE CHAPTER DESCRIPTION 13",
    "commodity": "SAMPLE COMMODITY 1"
  },
  "containerDetails": {
    "size": "40 HIGH CUBE",
    "type": "FLAT RACK",
    "quantity": 4
  },
  "routeDetails": {
    "placeOfReceipt": "SHANGHAI",
    "portOfLoading": "SHANGHAI",
    "portOfDischarge": "ALGECIRAS",
    "placeOfDelivery": "ALGECIRAS"
  },
  "scheduleDetails": {
    "estimatedArrivalAtLoadingPort": "2024-09-30 02:51",
    "estimatedDepartureFromLoadingPort": "2024-10-26 02:51",
    "estimatedArrivalAtDischargePort": "2024-11-24 02:51"
  },
  "emptyContainerPickupLocation": "YANTIAN, VIETNAM",
  "shippingTerm": "CIF",
  "remarks": "No special instructions",
  "transportationTerm": "CY/CY"
}