{
  "bookingReference": "CHERRY202410236601",
  "customerName": "CUSTOMER 6796",
  "shipperName": "SHIPPER 3065",
  "invoiceReceiver": "INVOICE RECEIVER 1613",
  "voyageDetails": {
    "vesselName": "APL MERLION",
    "voyageNumber": "2024721E"
  },
  "cargoDetails": {
    "hsCode": "674778",
    "chapterDescription": "SAMPLE CHAPTER DESCRIPTION 33",
    "commodity": "SAMPLE COMMODITY 97"
  },
  "containerDetails": {
    "size": "20 DRY",
    "type": "FLAT RACK",
    "quantity": 2
  },
  "routeDetails": {
    "placeOfReceipt": "ROTTERDAM",
    "portOfLoading": "ROTTERDAM",
    "portOfDischarge": "NINGBO",
    "placeOfDelivery": "NINGBO"
  },
  "scheduleDetails": {
    "estimatedArrivalAtLoadingPort": "2024-09-22 05:28",
    "estimatedDepartureFromLoadingPort": "2024-11-05 05:28",
    "estimatedArrivalAtDischargePort": "2024-11-23 05:28"
  },
  "emptyContainerPickupLocation": "TANGER, KOREA",
  "shippingTerm": "CIF",
  "remarks": "No special instructions"
}