{
  "bookingReference": "CHERRY202410287055",
  "customerName": "ALPHA IMPORT EXPORT LTD",
  "shipperName": "BETA MANUFACTURING CO.",
  "invoiceReceiver": "ALPHA IMPORT EXPORT LTD",
  "voyageDetails": {
    "vesselName": "CMA CGM GEORG FORSTER",
    "voyageNumber": "2432E"
  },
  "cargoDetails": {
    "hsCode": "84798990",
    "chapterDescription": "MACHINERY FOR WORKING TEXTILE FIBRES, NOT SPECIFIED OR INCLUDED ELSEWHERE IN THIS CHAPTER",
    "commodity": "TEXTILE MACHINERY"
  },
  "containerDetails": {
    "size": "40 HIGH CONTAINER",
    "type": "DRY",
    "quantity": 2
  },
  "routeDetails": {
    "placeOfReceipt": "NINGBO, CHINA",
    "portOfLoading": "NINGBO, CHINA",
    "portOfDischarge": "ALGECIRAS, SPAIN",
    "placeOfDelivery": "ALGECIRAS, SPAIN"
  },
  "scheduleDetails": {
    "estimatedArrivalAtLoadingPort": "2024-11-05 14:00",
    "estimatedDepartureFromLoadingPort": "2024-11-06 08:00",
    "estimatedArrivalAtDischargePort": "2024-11-28 12:00"
  },
  "emptyContainerPickupLocation": "NINGBO, CHINA",
  "shippingTerm": "CFR",
  "remarks": "Pre-shipment inspection required. 7 Days Free Time at Destination."
}