{
  "bookingReference": "CHERRY202409156689",
  "voyageDetails": {
    "vesselName": "CMA CGM ZHENG HE",
    "voyageNumber": "244EWT"
  },
  "routeDetails": {
    "placeOfReceipt": "NINGBO, CHINA",
    "portOfLoading": "NINGBO, CHINA",
    "portOfDischarge": "ROTTERDAM, NETHERLANDS",
    "placeOfDelivery": "ROTTERDAM, NETHERLANDS"
  },
  "paymentDetails": {
    "freightPaymentTerms": "COLLECT",
    "freightPayableAt": "ROTTERDAM, NETHERLANDS"
  },
  "documentationDetails": {
    "blType": "SEA WAYBILL",
    "numberOfOriginalBLs": 3,
    "numberOfCopies": 0
  },
  "partyDetails": {
    "shipper": {
      "name": "ASIA PACIFIC TRADING CO.",
      "onBehalfOf": "",
      "address": "228 HONGWU ROAD, SHANGHAI, CHINA 200001",
      "telephone": "+86-21-6327-1234",
      "fax": "+86-21-6327-5678"
    },
    "consignee": {
      "name": "GLOBAL SHIPPING SOLUTIONS INC.",
      "address": "123 MAIN STREET, NEW YORK, NY 10001, USA",
      "companyNumber": "12345678"
    },
    "notifyParty": {
      "name": "GLOBAL SHIPPING SOLUTIONS INC.",
      "address": "123 MAIN STREET, NEW YORK, NY 10001, USA"
    }
  },
  "shippingTerm": "CFR",
  "hsCode": "84798990",
  "commodityDescription": "TEXTILE LOOM SPARE PARTS",
  "containers": [
    {
      "containerNumber": "CMLU1234567",
      "sealNumber": "123456",
      "marksAndNumbers": "ASIA PACIFIC TRADING CO.",
      "numberOfPackages": 100,
      "packageType": "CARTONS",
      "cargoDescription": "TEXTILE LOOM SPARE PARTS AS PER PACKING LIST",
      "grossWeight": 12000.0,
      "measurement": 30.0,
      "additionalInfo": ""
    },
    {
      "containerNumber": "CMLU8765432",
      "sealNumber": "654321",
      "marksAndNumbers": "ASIA PACIFIC TRADING CO.",
      "numberOfPackages": 100,
      "packageType": "CARTONS",
      "cargoDescription": "TEXTILE LOOM SPARE PARTS AS PER PACKING LIST",
      "grossWeight": 12000.0,
      "measurement": 30.0,
      "additionalInfo": ""
    },
    {
      "containerNumber": "CMLU9876543",
      "sealNumber": "321654",
      "marksAndNumbers": "ASIA PACIFIC TRADING CO.",
      "numberOfPackages": 100,
      "packageType": "CARTONS",
      "cargoDescription": "TEXTILE LOOM SPARE PARTS AS PER PACKING LIST",
      "grossWeight": 12000.0,
      "measurement": 30.0,
      "additionalInfo": ""
    }
  ],
  "totalShipment": {
    "totalContainers": "THREE (40'HC) CONTAINERS",
    "totalPackages": 300,
    "packageType": "CARTONS",
    "containerType": "40'HC DRY",
    "totalGrossWeight": 36000.0,
    "totalMeasurement": 90.0
  },
  "additionalInformation": {
    "lcDetails": {
      "lcNumber": "LC1234567890"
    },
    "certificateDetails": [],
    "originalBLDistribution": {
      "name": "GLOBAL SHIPPING SOLUTIONS INC.",
      "address": "123 MAIN STREET, NEW YORK, NY 10001, USA",
      "telephone": "+1-212-555-1212",
      "fax": "+1-212-555-1213"
    },
    "originalInvoiceDistribution": {
      "name": "GLOBAL SHIPPING SOLUTIONS INC.",
      "address": "123 MAIN STREET, NEW YORK, NY 10001, USA",
      "telephone": "+1-212-555-1212",
      "fax": "+1-212-555-1213"
    },
    "onboardDate": "2024-09-22 12:00",
    "additionalRemarks": "SPECIAL HANDLING REQUIRED - FRAGILE CARGO"
  },
  "reeferSettings": {
    "containerNumber": "CRLU9908625",
    "temperature": "+5.0\u00baC",
    "minTemperature": "+2.0\u00b0C",
    "maxTemperature": "+7.0\u00b0C",
    "ventilation": "Closed",
    "humidity": "50% ~ 60%"
  }
}